README.md
setup.cfg
setup.py
argparseGraph/__init__.py
argparseGraph/argparseGraph.py
argparse_graph.egg-info/PKG-INFO
argparse_graph.egg-info/SOURCES.txt
argparse_graph.egg-info/dependency_links.txt
argparse_graph.egg-info/requires.txt
argparse_graph.egg-info/top_level.txt
test/test_main.py