Metadata-Version: 2.1
Name: argparse-graph
Version: 0.1.1
Summary: yaml file to add logique with argparse object.
Home-page: https://github.com/kuty22/argparse_graph
Author: Quentin Le Baron
Author-email: quentin.le-baron@epitech.eu
License: Apache 2.0
Platform: UNKNOWN
Classifier: Programming Language :: Python :: 3.6
Classifier: License :: OSI Approved :: Apache Software License
Classifier: Operating System :: OS Independent
